usr/share/ansible/roles/redhat-subscription/defaults/main.yml
usr/share/ansible/roles/redhat-subscription/library/rhsm_repository_conf.py
usr/share/ansible/roles/redhat-subscription/meta/main.yml
usr/share/ansible/roles/redhat-subscription/tasks/main.yml
usr/share/ansible/roles/redhat-subscription/tasks/portal.yml
usr/share/ansible/roles/redhat-subscription/tasks/register.yml
usr/share/ansible/roles/redhat-subscription/tasks/satellite-5.yml
usr/share/ansible/roles/redhat-subscription/tasks/satellite-6.yml
usr/share/ansible/roles/redhat-subscription/tasks/satellite.yml
usr/share/ansible/roles/redhat-subscription/tasks/unregister.yml
usr/share/ansible/roles/redhat-subscription/templates/rhsm.conf.j2
usr/share/ansible/roles/redhat-subscription/tests/Vagrantfile
usr/share/ansible/roles/redhat-subscription/tests/ansible.cfg
usr/share/ansible/roles/redhat-subscription/tests/vagrant.yml
usr/share/ansible/roles/redhat-subscription/tests/vars/portal.yml
usr/share/ansible/roles/redhat-subscription/vars/main.yml
ansible_role_redhat_subscription-1.3.0.dist-info/LICENSE
ansible_role_redhat_subscription-1.3.0.dist-info/METADATA
ansible_role_redhat_subscription-1.3.0.dist-info/WHEEL
ansible_role_redhat_subscription-1.3.0.dist-info/pbr.json
ansible_role_redhat_subscription-1.3.0.dist-info/top_level.txt
ansible_role_redhat_subscription-1.3.0.dist-info/RECORD
