Metadata-Version: 2.1
Name: ansible-role-redhat-subscription
Version: 1.3.0
Summary: ansible-role-redhat-subscription - An ansible role to Manage Red Hat subscritions and repositories
Home-page: https://github.com/openstack/ansible-role-redhat-subscription
Author: Sam Doran
Author-email: sdoran@redhat.com
License: UNKNOWN
Platform: UNKNOWN
Classifier: License :: OSI Approved :: Apache Software License
Classifier: Development Status :: 4 - Beta
Classifier: Intended Audience :: Developers
Classifier: Intended Audience :: System Administrators
Classifier: Intended Audience :: Information Technology
Classifier: Topic :: Utilities
Requires-Dist: pbr (>=1.6)
